Metadata-Version: 2.1
Name: CleanEmon-Admin
Version: 0.3
Summary: A set of useful admin-tools for the CleanEmon ecosystem
Author: George Vasiliadis
Author-email: geor.vasiliadis@gmail.com
Requires-Python: >=3.6
